Antennass/__init__.py
Antennass/antennass_cli.py
Antennass/antennass_gui.py
Antennass/arrays.py
Antennass-1.0.1.dist-info/METADATA
Antennass-1.0.1.dist-info/WHEEL
Antennass-1.0.1.dist-info/entry_points.txt
Antennass-1.0.1.dist-info/top_level.txt
Antennass-1.0.1.dist-info/RECORD
